{
  "name": "apiNG-plugin-instagram",
  "homepage": "https://github.com/JohnnyTheTank/apiNG-plugin-instagram",
  "authors": [
    "Jonathan Hornung <jonathan.hornung@gmail.com>"
  ],
  "version": "0.2.8",
  "description": "instagram plugin for apiNG",
  "main": "dist/angular-instagram-directive.min.js",
  "moduleType": [],
  "keywords": [
    "aping",
    "instagram",
    "angularjs",
    "rest",
    "api",
    "json"
  ],
  "license": "MIT",
  "ignore": [
    "**/.*",
    "node_modules",
    "bower_components",
    "test",
    "tests"
  ],
  "dependencies": {
    "angular-instagram-api-factory": "*",
    "apiNG": "*"
  },
  "_release": "0.2.8",
  "_resolution": {
    "type": "version",
    "tag": "v0.2.8",
    "commit": "2651f57e5d2e82888f24716406c4c57377d17bbe"
  },
  "_source": "git://github.com/JohnnyTheTank/apiNG-plugin-instagram.git",
  "_target": "*",
  "_originalSource": "apiNG-plugin-instagram"
}